redis_exec_retry.py
redis_exec_retry-0.0.2.dist-info/LICENSE
redis_exec_retry-0.0.2.dist-info/METADATA
redis_exec_retry-0.0.2.dist-info/WHEEL
redis_exec_retry-0.0.2.dist-info/top_level.txt
redis_exec_retry-0.0.2.dist-info/RECORD
