Metadata-Version: 2.1
Name: redis-exec-retry
Version: 0.0.2
Summary: redis-py that handles errors better.
Home-page: https://github.com/geonyoro/redis-exec-retry
Author: George Nyoro
Author-email: geonyoro@gmail.com
License: MIT License
Classifier: Development Status :: 5 - Production/Stable
Classifier: Intended Audience :: Developers
Classifier: License :: OSI Approved :: MIT License
Classifier: Operating System :: OS Independent
Classifier: Programming Language :: Python :: 3.5
Classifier: Programming Language :: Python :: 3.8
Classifier: Topic :: Software Development :: Libraries :: Python Modules
License-File: LICENSE
Requires-Dist: redis (>=4.6.0)
